Metadata-Version: 2.1
Name: autopvs1-batch
Version: 2.0
Summary: A tool for batch run autoPVS1
Home-page: UNKNOWN
Author: Ying Zhu
Author-email: win19890412@163.com
License: UNKNOWN
Platform: UNKNOWN
Classifier: Programming Language :: Python :: 3
Classifier: License :: OSI Approved :: MIT License
Classifier: Operating System :: OS Independent
